{
  "Multifaceted Varnish": {
    "name": "Multifaceted Varnish",
    "universalisId": "27695",
    "tomestonePrice": "5",
    "untradeable": false
  },

  "Multifaceted Abrasive": {
    "name": "Multifaceted Abrasive",
    "universalisId": "27718",
    "tomestonePrice": "5",
    "untradeable": false
  },

  "Multifaceted Resin": {
    "name": "Multifaceted Resin",
    "universalisId": "27719",
    "tomestonePrice": "5",
    "untradeable": false
  },

  "Multifaceted Alumen": {
    "name": "Multifaceted Alumen",
    "universalisId": "27744",
    "tomestonePrice": "5",
    "untradeable": false
  },

  "Multifaceted Cotton Cloth": {
    "name": "Multifaceted Cotton Cloth",
    "universalisId": "27762",
    "tomestonePrice": "5",
    "untradeable": false
  },

  "Multifaceted Alchemic": {
    "name": "Multifaceted Alchemic",
    "universalisId": "27796",
    "tomestonePrice": "5",
    "untradeable": false
  },

  "Chalicotherium Skin": {
    "name": "Chalicotherium Skin",
    "universalisId": "27737",
    "tomestonePrice": "5",
    "untradeable": false
  },

  "Dwarven Chromite": {
    "name": "Dwarven Chromite",
    "universalisId": "29969",
    "tomestonePrice": "10",
    "untradeable": false
  },

  "Workbench Resin": {
    "name": "Workbench Resin",
    "universalisId": "29971",
    "tomestonePrice": "10",
    "untradeable": false
  },

  "Tempest Adhesive": {
    "name": "Tempest Adhesive",
    "universalisId": "29973",
    "tomestonePrice": "10",
    "untradeable": false
  },

  "Caprice Fleece": {
    "name": "Caprice Fleece",
    "universalisId": "29975",
    "tomestonePrice": "10",
    "untradeable": false
  },

  "Megalania Skin": {
    "name": "Megalania Skin",
    "universalisId": "29977",
    "tomestonePrice": "10",
    "untradeable": false
  },

  "Dried Hi-Ether": {
    "name": "Dried Hi-Ether",
    "universalisId": "29979",
    "tomestonePrice": "10",
    "untradeable": false
  },

  "Aluminum Ore": {
    "name": "Aluminum Ore",
    "universalisId": "32945",
    "tomestonePrice": "20",
    "untradeable": false
  },

  "Workbench Refining Sand": {
    "name": "Workbench Refining Sand",
    "universalisId": "32946",
    "tomestonePrice": "20",
    "untradeable": false
  },

  "Thylacoleo Skin": {
    "name": "Thylacoleo Skin",
    "universalisId": "32948",
    "tomestonePrice": "20",
    "untradeable": false
  },

  "Gardenia Fruit": {
    "name": "Gardenia Fruit",
    "universalisId": "32947",
    "tomestonePrice": "20",
    "untradeable": false
  },

  "Horsetail": {
    "name": "Horsetail",
    "universalisId": "32944",
    "tomestonePrice": "20",
    "untradeable": false
  },

  "Spirit Extract": {
    "name": "Spirit Extract",
    "universalisId": "32949",
    "tomestonePrice": "20",
    "untradeable": false
  }
}
